find_asteroids/__init__.py
find_asteroids/_version.py
find_asteroids/cpu_impl.py
find_asteroids/directions.py
find_asteroids/gpu_impl.py
find_asteroids/postprocess.py
find_asteroids/primitives.py
find_asteroids/search.py
find_asteroids-0.1.3.dist-info/licenses/LICENSE
find_asteroids-0.1.3.dist-info/METADATA
find_asteroids-0.1.3.dist-info/WHEEL
find_asteroids-0.1.3.dist-info/entry_points.txt
find_asteroids-0.1.3.dist-info/top_level.txt
find_asteroids-0.1.3.dist-info/RECORD
