Metadata-Version: 2.4
Name: find-asteroids
Version: 0.1.3
Summary: Find moving objects in detection catalogs.
Author-email: Steven Stetzler <steven.stetzler@gmail.com>
License: MIT License
Project-URL: Source Code, https://github.com/stevenstetzler/find-asteroids
Classifier: Development Status :: 4 - Beta
Classifier: License :: OSI Approved :: MIT License
Classifier: Intended Audience :: Developers
Classifier: Intended Audience :: Science/Research
Classifier: Operating System :: OS Independent
Classifier: Programming Language :: Python
Requires-Python: >=3.9
License-File: LICENSE
Requires-Dist: astropy
Requires-Dist: numba
Requires-Dist: mcd-regression
Provides-Extra: dev
Requires-Dist: matplotlib; extra == "dev"
Requires-Dist: pytest; extra == "dev"
Dynamic: license-file
